HuobiAsyncWebsocket/HuobiAsyncWebsocket_pro.py
HuobiAsyncWebsocket/UrlParamsBuilder.py
HuobiAsyncWebsocket/__init__.py
HuobiAsyncWebsocket-1.2.1.dist-info/LICENSE
HuobiAsyncWebsocket-1.2.1.dist-info/METADATA
HuobiAsyncWebsocket-1.2.1.dist-info/WHEEL
HuobiAsyncWebsocket-1.2.1.dist-info/top_level.txt
HuobiAsyncWebsocket-1.2.1.dist-info/RECORD
